memememe.py
memememe-1.0.1.dist-info/licenses/LICENSE
memememe-1.0.1.dist-info/METADATA
memememe-1.0.1.dist-info/WHEEL
memememe-1.0.1.dist-info/top_level.txt
memememe-1.0.1.dist-info/RECORD
