Metadata-Version: 2.4
Name: memememe
Version: 1.0.1
Summary: A simple Python module to fetch random GIFs from Tenor.
Home-page: https://github.com/yourusername/memememe
Author: Seolhwa
Author-email: znzsndj@gmail.com
Classifier: Programming Language :: Python :: 3
Classifier: License :: OSI Approved :: MIT License
Classifier: Operating System :: OS Independent
Requires-Python: >=3.6
License-File: LICENSE
Requires-Dist: requests
Dynamic: author
Dynamic: author-email
Dynamic: classifier
Dynamic: description
Dynamic: description-content-type
Dynamic: home-page
Dynamic: license-file
Dynamic: requires-dist
Dynamic: requires-python
Dynamic: summary
